config/__init__.py
config/asgi.py
config/settings.py
config/urls.py
config/wsgi.py
extended_shell/__init__.py
extended_shell/apps.py
extended_shell/settings.py
extended_shell/startup.py
django_extended_shell-0.1.7.dist-info/METADATA
django_extended_shell-0.1.7.dist-info/WHEEL
django_extended_shell-0.1.7.dist-info/top_level.txt
django_extended_shell-0.1.7.dist-info/RECORD
