Metadata-Version: 2.1
Name: django-extended-shell
Version: 0.1.7
Summary: Django shell with imported models
Home-page: https://github.com/detect-dev/django-extended-shell
Author: Dmitry Bobrovitsky
Author-email: detect.dev@gmail.com
License: UNKNOWN
Platform: UNKNOWN
Classifier: Framework :: Django
Classifier: Programming Language :: Python :: 3
Classifier: License :: OSI Approved :: MIT License
Classifier: Operating System :: OS Independent
Requires-Python: >=3.6
